semdsl/__init__.py
semdsl/cli.py
semdsl/datamodel/semdsl_model.py
semdsl/datamodel/semdsl_model.yaml
semdsl/dsl_engine.py
semdsl/importers/__init__.py
semdsl/importers/importer.py
semdsl/importers/schema_importer.py
semdsl/mapper/__init__.py
semdsl/mapper/mapper.py
semdsl/view/__init__.py
semdsl/view/view.py
semdsl/writers/__init__.py
semdsl/writers/lark_writer.py
semdsl/writers/writer.py
semdsl-0.0.1rc1.dist-info/LICENSE
semdsl-0.0.1rc1.dist-info/METADATA
semdsl-0.0.1rc1.dist-info/WHEEL
semdsl-0.0.1rc1.dist-info/entry_points.txt
semdsl-0.0.1rc1.dist-info/RECORD
