Metadata-Version: 2.1
Name: semdsl
Version: 0.0.1rc1
Summary: semdsl
License: BSD-3
Author: LinkML Developers
Requires-Python: >=3.8,<4.0
Classifier: License :: Other/Proprietary License
Classifier: Programming Language :: Python :: 3
Classifier: Programming Language :: Python :: 3.8
Classifier: Programming Language :: Python :: 3.9
Classifier: Programming Language :: Python :: 3.10
Classifier: Programming Language :: Python :: 3.11
Provides-Extra: docs
Requires-Dist: inflection (>=0.5.1,<0.6.0)
Requires-Dist: lark (>=1.1.5,<2.0.0)
Requires-Dist: linkml-runtime (>=1.5.0)
